sphinx_nb_execution_patterns/__init__.py
sphinx_nb_execution_patterns/_version.py
sphinx_nb_execution_patterns-1.1.0.dist-info/METADATA
sphinx_nb_execution_patterns-1.1.0.dist-info/WHEEL
sphinx_nb_execution_patterns-1.1.0.dist-info/licenses/LICENSE
sphinx_nb_execution_patterns-1.1.0.dist-info/RECORD
