Metadata-Version: 2.4
Name: sphinx-nb-execution-patterns
Version: 1.1.0
Summary: A Sphinx extension to execute Jupyter NoteBooks based on include and exclude patterns instead of only exclude patterns.
Author-email: Dennis den Ouden-van der Horst <d.denouden-vanderhorst@tudelft.nl>
License: MIT License
License-File: LICENSE
Requires-Python: >=3.10
Requires-Dist: jupyterbook-patches>=1.12.1
Requires-Dist: sphinx
